snipsmanager/__init__.py
snipsmanager/cli.py
snipsmanager/snipsmanager
snipsmanager/commands/__init__.py
snipsmanager/commands/base.py
snipsmanager/commands/run.py
snipsmanager/commands/scaffold.py
snipsmanager/commands/assistant/__init__.py
snipsmanager/commands/assistant/fetch.py
snipsmanager/commands/assistant/load.py
snipsmanager/commands/install/__init__.py
snipsmanager/commands/install/addon.py
snipsmanager/commands/install/bluetooth.py
snipsmanager/commands/install/install.py
snipsmanager/commands/install/skill.py
snipsmanager/commands/install/skills.py
snipsmanager/commands/session/__init__.py
snipsmanager/commands/session/login.py
snipsmanager/commands/session/logout.py
snipsmanager/commands/setup/__init__.py
snipsmanager/commands/setup/microphone.py
snipsmanager/commands/setup/speaker.py
snipsmanager/commands/setup/systemd/__init__.py
snipsmanager/commands/setup/systemd/bluetooth.py
snipsmanager/commands/setup/systemd/snipsmanager.py
snipsmanager/config/__init__.py
snipsmanager/config/asound.conf/__init__.py
snipsmanager/config/asound.conf/asound.conf.default
snipsmanager/config/asound.conf/asound.conf.jabra
snipsmanager/config/asound.conf/asound.conf.respeaker
snipsmanager/config/asound.conf/asound.conf.speakerbonnet
snipsmanager/config/asound.conf/asoundrc.speakerbonnet
snipsmanager/config/drivers/__init__.py
snipsmanager/config/drivers/adafruit_bonnet.sh
snipsmanager/config/systemd/__init__.py
snipsmanager/config/systemd/snipsble.service
snipsmanager/config/systemd/snipsmanager.service
snipsmanager/models/__init__.py
snipsmanager/models/dialoguedef.py
snipsmanager/models/intentdef.py
snipsmanager/models/notificationdef.py
snipsmanager/models/skilldef.py
snipsmanager/templates/LICENSE.txt
snipsmanager/templates/MANIFEST.in
snipsmanager/templates/README.rst
snipsmanager/templates/__init__.py
snipsmanager/templates/intent_registry_template.py
snipsmanager/templates/intent_template.py
snipsmanager-0.1.6.42.dist-info/DESCRIPTION.rst
snipsmanager-0.1.6.42.dist-info/METADATA
snipsmanager-0.1.6.42.dist-info/RECORD
snipsmanager-0.1.6.42.dist-info/WHEEL
snipsmanager-0.1.6.42.dist-info/entry_points.txt
snipsmanager-0.1.6.42.dist-info/metadata.json
snipsmanager-0.1.6.42.dist-info/top_level.txt
