Metadata-Version: 2.0
Name: snipsmanager
Version: 0.1.6.42
Summary: Snips Manager
Home-page: https://github.com/snipsco/snipsmanager
Author: Snips
Author-email: labs@snips.ai
License: MIT
Keywords: cli,snips
Platform: UNKNOWN
Requires-Dist: Jinja2
Requires-Dist: docopt
Requires-Dist: pip
Requires-Dist: python-dateutil
Requires-Dist: pyyaml
Requires-Dist: snipsmanagercore (>=0.1.6.0.4)
Provides-Extra: test
Requires-Dist: coverage; extra == 'test'
Requires-Dist: pytest; extra == 'test'
Requires-Dist: pytest-cov; extra == 'test'
